doyle/__init__.py
doyle/config.py
doyle/data_exploration.py
doyle/preprocessing.py
doyle/features/__init__.py
doyle/sherlock_assistance/__init__.py
doyle/sherlock_assistance/model.py
doyle/sherlock_assistance/word_embeddings.py
doyle/statics/category_variable_conf_30-1500_viznet_dataset_threshold.bin
doyle/statics/fsign.json
doyle/utils/__init__.py
doyle/utils/theme.py
doyle-0.0.0.dev29.dist-info/LICENSE
doyle-0.0.0.dev29.dist-info/METADATA
doyle-0.0.0.dev29.dist-info/WHEEL
doyle-0.0.0.dev29.dist-info/top_level.txt
doyle-0.0.0.dev29.dist-info/RECORD
